magicplot/__init__.py
magicplot/_version.py
magicplot/analysisPane.py
magicplot/analysisPane.ui
magicplot/analysisPane_ui.py
magicplot/analysisPlugins.py
magicplot/grid.py
magicplot/magicPlot.ui
magicplot/magicPlot_ui.py
magicplot/magicplot.py
magicplot/shapeDrawer.py
magicplot/shapeDrawer.ui
magicplot/shapeDrawer_ui.py
magicplot/shapeHolder.py
magicplot/transformPlugins.py
magicplot/transforms.py
magicplot/plugins/__init__.py
magicplot/plugins/analysis/Average.py
magicplot/plugins/analysis/Gradient.py
magicplot/plugins/analysis/ShowData.py
magicplot/plugins/analysis/Strehl.py
magicplot/plugins/analysis/__init__.py
magicplot/plugins/analysis/code.py
magicplot/plugins/transforms/__init__.py
magicplot/plugins/transforms/add.py
magicplot/plugins/transforms/fft2d.py
magicplot/plugins/transforms/log.py
magicplot-0.1.post121.dist-info/licenses/LICENSE
magicplot-0.1.post121.dist-info/METADATA
magicplot-0.1.post121.dist-info/WHEEL
magicplot-0.1.post121.dist-info/top_level.txt
magicplot-0.1.post121.dist-info/RECORD
