Metadata-Version: 2.4
Name: magicplot
Version: 0.1.post121
Summary: A generalised, powerful plotting tool for science
Author-email: Ollie Farley <o.j.d.farley@durham.ac.uk>
Project-URL: Homepage, https://github.com/ojdf/magicplot
Classifier: Programming Language :: Python :: 3
Requires-Python: >=3.7
License-File: LICENSE
Requires-Dist: numpy
Requires-Dist: pyqtgraph
Requires-Dist: PyQt5
Requires-Dist: scipy
Dynamic: license-file
